{
    "num": 1,
    "date": "2020-12-08 17:11:33",
    "media_id": "2459770312837006907",
    "shortcode": "CIi3BEts4Y7",
    "display_url": "https://scontent-lhr8-2.cdninstagram.com/v/t51.29350-15/130287743_919997598532710_23923624242622019_n.jpg?stp=dst-jpg_e35_tt6&efg=eyJ2ZW5jb2RlX3RhZyI6IkZFRUQuaW1hZ2VfdXJsZ2VuLjEwODB4MTM1MC5zZHIuZjI5MzUwLmRlZmF1bHRfaW1hZ2UuYzIifQ&_nc_ht=scontent-lhr8-2.cdninstagram.com&_nc_cat=106&_nc_oc=Q6cZ2QE5mJEJrzWEgFMh5EIFSoOy4PInhEYslZj7vJzk-BhzQwFRhifDBok_u-4GT0KVg6ufpejmFm6h6wsA8MkijBTN&_nc_ohc=x39g3WsXmGsQ7kNvwFIRr40&_nc_gid=J3bAswBMyRPZEWH-fImLUw&edm=ACOOH6wBAAAA&ccb=7-5&ig_cache_key=MjQ1OTc3MDMxMjgzNzAwNjkwNw%3D%3D.3-ccb7-5&oh=00_AfdpuBYhzIFSVS5yhygkHFRhiQmj1c6BSWC6ilMCIulxCw&oe=69068089&_nc_sid=aa4e97",
    "video_url": null,
    "width": 1080,
    "height": 1350,
    "owner": {
        "fbid_v2": "17841422569615960",
        "feed_post_reshare_disabled": false,
        "full_name": "Amazingshots_castle",
        "id": "22687680320",
        "is_unpublished": false,
        "pk": "22687680320",
        "pk_id": "22687680320",
        "strong_id__": "22687680320",
        "third_party_downloads_enabled": 1,
        "can_see_quiet_post_attribution": true,
        "account_type": 2,
        "account_badges": [],
        "fan_club_info": {
            "autosave_to_exclusive_highlight": null,
            "connected_member_count": null,
            "fan_club_id": null,
            "fan_club_name": null,
            "has_created_ssc": null,
            "has_enough_subscribers_for_ssc": null,
            "is_fan_club_gifting_eligible": null,
            "is_fan_club_referral_eligible": null,
            "is_free_trial_eligible": null,
            "largest_public_bc_id": null,
            "subscriber_count": null,
            "should_show_playlists_in_profile_tab": null,
            "fan_consideration_page_revamp_eligiblity": null
        },
        "friendship_status": {
            "following": false,
            "is_bestie": false,
            "is_feed_favorite": false,
            "is_private": false,
            "is_restricted": false,
            "followed_by": false,
            "is_muting_reel": false
        },
        "has_anonymous_profile_picture": false,
        "hd_profile_pic_url_info": {
            "height": 1006,
            "url": "https://scontent-lhr6-2.cdninstagram.com/v/t51.2885-19/75306161_738038320005388_6362874752012386304_n.jpg?efg=eyJ2ZW5jb2RlX3RhZyI6InByb2ZpbGVfcGljLmRqYW5nby4xMDA2LmMyIn0&_nc_ht=scontent-lhr6-2.cdninstagram.com&_nc_cat=104&_nc_oc=Q6cZ2QE5mJEJrzWEgFMh5EIFSoOy4PInhEYslZj7vJzk-BhzQwFRhifDBok_u-4GT0KVg6ufpejmFm6h6wsA8MkijBTN&_nc_ohc=8nsxs0g-ro0Q7kNvwHSr3uh&_nc_gid=J3bAswBMyRPZEWH-fImLUw&edm=ACOOH6wBAAAA&ccb=7-5&oh=00_Afez9twZKkHGejs_ucVlIve3GiUrGviSJYuMgDjRtJmBDA&oe=690699DB&_nc_sid=aa4e97",
            "width": 1006
        },
        "hd_profile_pic_versions": [
            {
                "height": 320,
                "url": "https://scontent-lhr6-2.cdninstagram.com/v/t51.2885-19/75306161_738038320005388_6362874752012386304_n.jpg?stp=dst-jpg_s320x320_tt6&efg=eyJ2ZW5jb2RlX3RhZyI6InByb2ZpbGVfcGljLmRqYW5nby4xMDA2LmMyIn0&_nc_ht=scontent-lhr6-2.cdninstagram.com&_nc_cat=104&_nc_oc=Q6cZ2QE5mJEJrzWEgFMh5EIFSoOy4PInhEYslZj7vJzk-BhzQwFRhifDBok_u-4GT0KVg6ufpejmFm6h6wsA8MkijBTN&_nc_ohc=8nsxs0g-ro0Q7kNvwHSr3uh&_nc_gid=J3bAswBMyRPZEWH-fImLUw&edm=ACOOH6wBAAAA&ccb=7-5&oh=00_AfeBOBFeyalWkDX9hW3IwLEcHAx1GkbbwaBdWb_pm49M_Q&oe=690699DB&_nc_sid=aa4e97",
                "width": 320
            },
            {
                "height": 640,
                "url": "https://scontent-lhr6-2.cdninstagram.com/v/t51.2885-19/75306161_738038320005388_6362874752012386304_n.jpg?stp=dst-jpg_s640x640_tt6&efg=eyJ2ZW5jb2RlX3RhZyI6InByb2ZpbGVfcGljLmRqYW5nby4xMDA2LmMyIn0&_nc_ht=scontent-lhr6-2.cdninstagram.com&_nc_cat=104&_nc_oc=Q6cZ2QE5mJEJrzWEgFMh5EIFSoOy4PInhEYslZj7vJzk-BhzQwFRhifDBok_u-4GT0KVg6ufpejmFm6h6wsA8MkijBTN&_nc_ohc=8nsxs0g-ro0Q7kNvwHSr3uh&_nc_gid=J3bAswBMyRPZEWH-fImLUw&edm=ACOOH6wBAAAA&ccb=7-5&oh=00_AfesqcK0o7q9sWjXy-m7b8UxQ24WNahy1qLkaO1HVtyAWA&oe=690699DB&_nc_sid=aa4e97",
                "width": 640
            }
        ],
        "is_favorite": false,
        "is_private": false,
        "is_ring_creator": false,
        "show_ring_award": false,
        "is_verified": false,
        "profile_pic_id": "2186357993023708483_22687680320",
        "profile_pic_url": "https://scontent-lhr6-2.cdninstagram.com/v/t51.2885-19/75306161_738038320005388_6362874752012386304_n.jpg?stp=dst-jpg_s150x150_tt6&efg=eyJ2ZW5jb2RlX3RhZyI6InByb2ZpbGVfcGljLmRqYW5nby4xMDA2LmMyIn0&_nc_ht=scontent-lhr6-2.cdninstagram.com&_nc_cat=104&_nc_oc=Q6cZ2QE5mJEJrzWEgFMh5EIFSoOy4PInhEYslZj7vJzk-BhzQwFRhifDBok_u-4GT0KVg6ufpejmFm6h6wsA8MkijBTN&_nc_ohc=8nsxs0g-ro0Q7kNvwHSr3uh&_nc_gid=J3bAswBMyRPZEWH-fImLUw&edm=ACOOH6wBAAAA&ccb=7-5&oh=00_AffbHtCg0m4JfpEXraaRnK4rNi2i1xPgvuCc2sLnEl4bFw&oe=690699DB&_nc_sid=aa4e97",
        "show_account_transparency_details": true,
        "transparency_product_enabled": false,
        "username": "amazingshots_castle",
        "is_embeds_disabled": false,
        "is_active_on_text_post_app": false,
        "latest_reel_media": 1761653341,
        "eligible_for_text_app_activation_badge": false,
        "user_activation_info": {}
    },
    "tagged_users": [
        {
            "id": "1380485",
            "username": "massaro_dani",
            "full_name": "Daniele Massaro"
        }
    ],
    "post_id": "2459770312837006907",
    "post_shortcode": "CIi3BEts4Y7",
    "likes": 3968,
    "liked": false,
    "pinned": [],
    "description": "CONGRATS to\n📷 : @massaro_dani\nID tag #amzctl_massaro_dani\n\n📌 Luogo ~ Place : Italy 🇮🇹 \n\nSelected by ADMIN : @currelistefania\n\nOwner @irmopradelli\n\nFOLLOW  @amazingshots_castle\n\nTAG #amazingshots_castle\n# amazingscastle\n# amazing_castle\n\nCOMMUNITY @amazingshots_community\n\nFriendly gallery\n👉 @castlesofspain\n\n🔴Appreciated Repost🔴\n\n🚫Only your photos-no web pics-no stolen pics🚫\n....\nRocca Calascio è una rocca situata in Abruzzo, in provincia dell'Aquila, nel territorio di Calascio, ad un'altitudine di 1 460 m s.l.m.\nDi origine medievale, è conosciuta per la presenza del castello, tra i più elevati d'Italia, considerato uno dei simboli dell'Abruzzo. La rocca, baricentrica tra l'altopiano di Campo Imperatore e quelli sottostanti di Navelli e del Tirino, è inserita in un contesto di grande valore paesaggistico e ricompresa nel Parco Nazionale del Gran Sasso e Monti della Laga di cui costituisce una delle principali mete turistiche.\n....\n🔹️🔸️🔹️🔸️🔹️🔸️🔹️🔸️🔹️🔸️🔹️🔸️🔹️\n#castlemypassion\n#loves_united_castle\n#castles_oftheworld\n#castleoftheworld\n#castlephotography\n#medievalcastle\n#medievalarchitecture\n#historicalbuildings\n#monumentalworld\n#beniculturali30\n#instacastle\n#castlelovers\n#oldarchitecture\n#historicalarchitecture\n#historicplace\n#unescoworldheritagesite\n#beautifularchitecture\n#castlehoward\n#castleofinstagram\n#europeancastles\n#oldstones\n#medievaltown\n#castellidelmondo\n#beautiful_destinations\n#churchmypassion\n#living_europe \n#monumentaleurope \n#fiftyshades_of_history",
    "tags": [
        "#amazingshots_castle",
        "#amzctl_massaro_dani",
        "#beautiful_destinations",
        "#beautifularchitecture",
        "#beniculturali30",
        "#castellidelmondo",
        "#castlehoward",
        "#castlelovers",
        "#castlemypassion",
        "#castleofinstagram",
        "#castleoftheworld",
        "#castlephotography",
        "#castles_oftheworld",
        "#churchmypassion",
        "#europeancastles",
        "#fiftyshades_of_history",
        "#historicalarchitecture",
        "#historicalbuildings",
        "#historicplace",
        "#instacastle",
        "#living_europe",
        "#loves_united_castle",
        "#medievalarchitecture",
        "#medievalcastle",
        "#medievaltown",
        "#monumentaleurope",
        "#monumentalworld",
        "#oldarchitecture",
        "#oldstones",
        "#unescoworldheritagesite"
    ],
    "location_id": "414191472",
    "location_slug": "rocca-calascio",
    "location_url": "https://www.instagram.com/explore/locations/414191472/rocca-calascio/",
    "owner_id": "22687680320",
    "username": "amazingshots_castle",
    "fullname": "Amazingshots_castle",
    "post_date": "2020-12-08 17:11:33",
    "type": "post",
    "post_url": "https://www.instagram.com/p/CIi3BEts4Y7/",
    "count": 1,
    "category": "instagram",
    "subcategory": "saved",
    "filename": "130287743_919997598532710_23923624242622019_n",
    "extension": "jpg"
}
